quantec/__init__.py
quantec/easydata/__init__.py
quantec/easydata/cache.py
quantec/easydata/client.py
quantec/easydata/validators.py
quantec-0.4.4.dist-info/METADATA
quantec-0.4.4.dist-info/WHEEL
quantec-0.4.4.dist-info/licenses/LICENSE.txt
quantec-0.4.4.dist-info/RECORD
