Metadata-Version: 2.4
Name: quantec
Version: 0.4.4
Summary: A Python package for working with Quantec EasyData.
Project-URL: Homepage, https://www.quantec.co.za/easydata/
Project-URL: Repository, https://github.com/quantecresearch/quantec-python
Author-email: David de Wet <david@quantec.co.za>
License: MIT License
License-File: LICENSE.txt
Requires-Python: >=3.10
Requires-Dist: numpy>=2.2.6
Requires-Dist: pandas>=2.2.3
Requires-Dist: pyarrow>=18.0.0
Requires-Dist: python-dotenv>=1.0.0
Requires-Dist: requests>=2.28.0
Provides-Extra: dev
Requires-Dist: pytest-cov>=4.0.0; extra == 'dev'
Requires-Dist: pytest-env>=1.0.0; extra == 'dev'
Requires-Dist: pytest>=7.0.0; extra == 'dev'
